{
  "db_name": "PostgreSQL",
  "query": "SELECT ai_resource, code_completion_model, ai_models FROM workspace_settings WHERE workspace_id = $1",
  "describe": {
    "columns": [
      {
        "ordinal": 0,
        "name": "ai_resource",
        "type_info": "Jsonb"
      },
      {
        "ordinal": 1,
        "name": "code_completion_model",
        "type_info": "Varchar"
      },
      {
        "ordinal": 2,
        "name": "ai_models",
        "type_info": "VarcharArray"
      }
    ],
    "parameters": {
      "Left": [
        "Text"
      ]
    },
    "nullable": [
      true,
      true,
      false
    ]
  },
  "hash": "b186efe51e7bb1924efbd7e9b36085502a1e77e30e59c7310c78976f77a810a3"
}
