{
  "db_name": "PostgreSQL",
  "query": "INSERT INTO flow (workspace_id, path, summary, description, value, edited_by, edited_at, schema, dependency_job, draft_only, tag, dedicated_worker, visible_to_runner_only) VALUES ($1, $2, $3, $4, $5, $6, now(), $7::text::json, NULL, $8, $9, $10, $11)",
  "describe": {
    "columns": [],
    "parameters": {
      "Left": [
        "Varchar",
        "Varchar",
        "Text",
        "Text",
        "Jsonb",
        "Varchar",
        "Text",
        "Bool",
        "Varchar",
        "Bool",
        "Bool"
      ]
    },
    "nullable": []
  },
  "hash": "35e6af0b203e3e4fac9020b037a3c41af92537c0fd5683227767f6a1bd17339f"
}
