{
  "db_name": "PostgreSQL",
  "query": "INSERT INTO job_resolution (job_id, workspace_id, resolved_by, note)\n            SELECT c.id, c.workspace_id, NULL, NULL\n                FROM v2_job_completed c\n                JOIN v2_job j ON j.id = c.id\n                WHERE c.status = 'failure'\n                    AND c.workspace_id = $2\n                    AND j.runnable_id IS NOT DISTINCT FROM $4\n                    AND EXISTS (\n                        SELECT 1 FROM v2_job_completed sc\n                        JOIN v2_job sj ON sj.id = sc.id\n                        JOIN native_retry_attempt nra ON nra.job_id = sc.id\n                        WHERE sc.id = $3\n                            AND sc.status = 'success'\n                            AND sc.workspace_id = $2\n                            AND sj.parent_job = $1\n                            AND sj.runnable_id IS NOT DISTINCT FROM $4\n                    )\n                    AND (\n                        (j.parent_job = $1\n                            AND EXISTS (SELECT 1 FROM native_retry_attempt WHERE job_id = c.id))\n                        OR (c.id = $1 AND j.parent_job IS NULL\n                            AND NOT EXISTS (SELECT 1 FROM native_retry_attempt WHERE job_id = c.id))\n                    )\n            ON CONFLICT (job_id) DO NOTHING",
  "describe": {
    "columns": [],
    "parameters": {
      "Left": [
        "Uuid",
        "Text",
        "Uuid",
        "Int8"
      ]
    },
    "nullable": []
  },
  "hash": "008e0d4d884c150e59250bff6e8c552cfc41bdf6ef5c84871e97c3eaac09778f"
}
