{
  "db_name": "PostgreSQL",
  "query": "SELECT permissioned_as, edited_by FROM websocket_trigger WHERE path = $1 AND workspace_id = $2",
  "describe": {
    "columns": [
      {
        "ordinal": 0,
        "name": "permissioned_as",
        "type_info": "Varchar"
      },
      {
        "ordinal": 1,
        "name": "edited_by",
        "type_info": "Varchar"
      }
    ],
    "parameters": {
      "Left": [
        "Text",
        "Text"
      ]
    },
    "nullable": [
      false,
      false
    ]
  },
  "hash": "39062cdb183b97906c25602000321a76d4e629ba027364190a2487cc9bd93235"
}
