{
  "db_name": "PostgreSQL",
  "query": "UPDATE v2_queue SET flow_status = jsonb_set(COALESCE(flow_status, '{}'::jsonb), array[$1], jsonb_set(jsonb_set('{}'::jsonb, '{scheduled_for}', to_jsonb(now()::text)), '{name}', to_jsonb($4::text))) WHERE id = $2 AND workspace_id = $3",
  "describe": {
    "columns": [],
    "parameters": {
      "Left": [
        "Text",
        "Uuid",
        "Text",
        "Text"
      ]
    },
    "nullable": []
  },
  "hash": "7a706906e461df376f5238fd1dda387ab71bc0c9d9ad0c3e7737138adb6cc224"
}
