{
  "db_name": "PostgreSQL",
  "query": "SELECT created_by, extra_perms FROM volume WHERE workspace_id = $1 AND name = $2",
  "describe": {
    "columns": [
      {
        "ordinal": 0,
        "name": "created_by",
        "type_info": "Varchar"
      },
      {
        "ordinal": 1,
        "name": "extra_perms",
        "type_info": "Jsonb"
      }
    ],
    "parameters": {
      "Left": [
        "Text",
        "Text"
      ]
    },
    "nullable": [
      false,
      false
    ]
  },
  "hash": "6086849bb08e1b37d6693d2808767cd897dca4722e4f2076308afdb7ee9fc147"
}
