{
  "db_name": "PostgreSQL",
  "query": "SELECT DISTINCT ON (path) path AS \"path!\", content AS \"content!\"\n               FROM script\n               WHERE workspace_id = $1\n                 AND auto_kind = 'pipeline'\n                 AND language = 'duckdb'::script_lang\n                 AND archived = false\n                 AND deleted = false\n                 AND path != $2\n               ORDER BY path, created_at DESC",
  "describe": {
    "columns": [
      {
        "ordinal": 0,
        "name": "path!",
        "type_info": "Varchar"
      },
      {
        "ordinal": 1,
        "name": "content!",
        "type_info": "Text"
      }
    ],
    "parameters": {
      "Left": [
        "Text",
        "Text"
      ]
    },
    "nullable": [
      false,
      false
    ]
  },
  "hash": "198cd40f80f2f5211dd93d960e47b38ec4019726be9e89fb58929cc3b597c10d"
}
