{
  "db_name": "PostgreSQL",
  "query": "WITH del AS (\n            DELETE FROM v2_job_debounce_batch\n            WHERE consumed_at IS NOT NULL AND consumed_at < now() - interval '1 hour'\n            RETURNING 1\n        ) SELECT count(*) FROM del",
  "describe": {
    "columns": [
      {
        "ordinal": 0,
        "name": "count",
        "type_info": "Int8"
      }
    ],
    "parameters": {
      "Left": []
    },
    "nullable": [
      null
    ]
  },
  "hash": "70f01b322765442de8888b6d9b79984da751f9ae10c8b15ada925bd371501e18"
}
