{
  "db_name": "PostgreSQL",
  "query": "INSERT INTO v2_job_queue (id, workspace_id, tag, running, scheduled_for,\n                                           concurrency_gated_at, concurrency_gate_id)\n                 VALUES ($1, 'test-workspace', $2, false, NOW() - INTERVAL '5 minutes',\n                         CASE WHEN $3::bigint IS NULL THEN NULL\n                              ELSE NOW() - INTERVAL '1 second' * $3::bigint END,\n                         $4)",
  "describe": {
    "columns": [],
    "parameters": {
      "Left": [
        "Uuid",
        "Varchar",
        "Int8",
        "Varchar"
      ]
    },
    "nullable": []
  },
  "hash": "ad143b4b7b6a716326e900d30d8f05f515a2c1bda560368bf5517ba5d18292f3"
}
