{
  "db_name": "PostgreSQL",
  "query": "\n        INSERT INTO schedule (\n            workspace_id, path, edited_by, schedule, enabled,\n            script_path, is_flow, email, timezone\n        )\n        VALUES ($1, $2, $3, $4, $5, $6, $7, $8, $9)\n        ",
  "describe": {
    "columns": [],
    "parameters": {
      "Left": [
        "Varchar",
        "Varchar",
        "Varchar",
        "Varchar",
        "Bool",
        "Varchar",
        "Bool",
        "Varchar",
        "Varchar"
      ]
    },
    "nullable": []
  },
  "hash": "75ce9753a8acc8eccb3f2e0baaa5a871f866a8d21961fac8a003bc40c406ee79"
}
