{
  "db_name": "PostgreSQL",
  "query": "\n                WITH live_gates AS (\n                    SELECT concurrency_gated_key AS key\n                    FROM v2_job_queue\n                    WHERE tag = $1 AND running = false\n                      AND concurrency_gated_key IS NOT NULL\n                    GROUP BY concurrency_gated_key\n                    HAVING MAX(concurrency_gated_at) >= NOW() - $2::interval\n                )\n                SELECT COUNT(*) FILTER (WHERE overdue AND g.key IS NULL) AS ungated_count,\n                       COUNT(*) FILTER (WHERE overdue AND g.key IS NOT NULL) AS gated_count,\n                       MIN(q.scheduled_for) FILTER (WHERE overdue AND g.key IS NULL)\n                           AS oldest_ungated,\n                       MIN(q.scheduled_for) FILTER (WHERE overdue) AS oldest_overdue\n                FROM (\n                    SELECT scheduled_for, concurrency_gated_key,\n                           scheduled_for <= NOW() - $2::interval AS overdue\n                    FROM v2_job_queue\n                    WHERE tag = $1 AND running = false\n                ) q\n                LEFT JOIN live_gates g ON g.key = q.concurrency_gated_key\n                ",
  "describe": {
    "columns": [
      {
        "ordinal": 0,
        "name": "ungated_count",
        "type_info": "Int8"
      },
      {
        "ordinal": 1,
        "name": "gated_count",
        "type_info": "Int8"
      },
      {
        "ordinal": 2,
        "name": "oldest_ungated",
        "type_info": "Timestamptz"
      },
      {
        "ordinal": 3,
        "name": "oldest_overdue",
        "type_info": "Timestamptz"
      }
    ],
    "parameters": {
      "Left": [
        "Text",
        "Interval"
      ]
    },
    "nullable": [
      null,
      null,
      null,
      null
    ]
  },
  "hash": "ecddc3a6edae10ed258ce600167f454e5a3e2b523278988d4bfdc6060e041a58"
}
